<?xml version="1.0" encoding="utf-8"?>
<vah:VahvistettavaLaki xmlns:vah="http://www.vn.fi/skeemat/vahvistettavalaki/2010/04/27" xmlns:sdk="http://www.finlex.fi/skeemat/edita/sdk/2010/04/27" xmlns:saa="http://www.vn.fi/skeemat/saadoskooste/2010/04/27" xmlns:saa1="http://www.vn.fi/skeemat/saadoselementit/2010/04/27" xmlns:met="http://www.vn.fi/skeemat/metatietokooste/2010/04/27" xmlns:met1="http://www.vn.fi/skeemat/metatietoelementit/2010/04/27" xmlns:asi="http://www.vn.fi/skeemat/asiakirjakooste/2010/04/27" xmlns:asi1="http://www.vn.fi/skeemat/asiakirjaelementit/2010/04/27" xmlns:org="http://www.vn.fi/skeemat/organisaatiokooste/2010/02/15" xmlns:org1="http://www.vn.fi/skeemat/organisaatioelementit/2010/02/15" xmlns:tau="http://www.vn.fi/skeemat/taulukkokooste/2010/04/27" xmlns:sis="http://www.vn.fi/skeemat/sisaltokooste/2010/04/27" xmlns:sis1="http://www.vn.fi/skeemat/sisaltoelementit/2010/04/27" met1:kieliKoodi="fi" met1:julkisuusKoodi="julkinen" met1:tilaKoodi="Valmis" met1:identifiointiTunnus="0000000000000000" met1:versioTeksti="1.0" met1:asiakirjatyyppiNimi="Vahvistettava laki" met1:laadintaPvm="2100-01-01" met1:rakennemaarittelyNimi="vahvistettavalaki.xsd">
  <asi:IdentifiointiOsa>
    <met1:AsiakirjatyyppiNimi>Vahvistettava laki</met1:AsiakirjatyyppiNimi>
    <asi:EduskuntaTunniste>
      <met1:AsiakirjatyyppiKoodi>SDK</met1:AsiakirjatyyppiKoodi>
      <asi1:AsiakirjaNroTeksti>1085</asi1:AsiakirjaNroTeksti>
      <asi1:ValtiopaivavuosiTeksti>1987</asi1:ValtiopaivavuosiTeksti>
    </asi:EduskuntaTunniste>
    <met:Nimeke>
      <met1:NimekeTeksti>liikenneministeriöstä annetun asetuksen muuttamisesta</met1:NimekeTeksti>
    </met:Nimeke>
  </asi:IdentifiointiOsa>
  <saa:SaadosOsa>
    <saa:Saados met1:kieliKoodi="fi" saa1:saadostyyppiNimi="Asetus">
      <saa:SaadosNimeke>
        <saa:SaadostyyppiKooste>Asetus</saa:SaadostyyppiKooste>
        <saa:SaadosNimekeKooste>liikenneministeriöstä annetun asetuksen muuttamisesta</saa:SaadosNimekeKooste>
      </saa:SaadosNimeke>
      <saa:Johtolause>
        <saa:SaadosKappaleKooste>Liikenneministerin esittelystä</saa:SaadosKappaleKooste>
        <saa:SaadosKappaleKooste><saa:SaadosKursiiviKooste>kumotaan </saa:SaadosKursiiviKooste>liikenneministeriöstä 15 päivänä helmikuuta 1985 annetun asetuksen (198/85) 21 a§, sellaisena kuin se on lisättynä 28 päivänä helmikuuta 1986 annetussa asetuksessa (184/86),</saa:SaadosKappaleKooste>
        <saa:SaadosKappaleKooste><saa:SaadosKursiiviKooste>muutetaan</saa:SaadosKursiiviKooste> 8-10§ sekä 21, 22 ja 26§,</saa:SaadosKappaleKooste>
        <saa:SaadosKappaleKooste>sellaisina kuin niistä ovat 8§:n 1 momentti ja 10§:n 2 momentti 13 päivänä helmikuuta 1987 annetussa asetuksessa (120/87), 9§ osittain muutettuna 10 päivänä toukokuuta 1985 annetussa asetuksessa (380/85), 28 päivänä helmikuuta 1986 annetussa asetuksessa (184/86) ja mainitussa 13 päivänä helmikuuta 1987 annetussa asetuksessa sekä 10§:n 3 momentti mainitussa 28 päivänä helmikuuta 1986 annetussa asetuksessa, ja</saa:SaadosKappaleKooste>
        <saa:SaadosKappaleKooste><saa:SaadosKursiiviKooste>lisätään</saa:SaadosKursiiviKooste> asetuksen 11§:ään uusi 3 momentti, seuraavasti:</saa:SaadosKappaleKooste>
      </saa:Johtolause>
      <saa:Pykalisto>
        <saa:SaadosValiotsikkoKooste>Ministeriön virkamiehet ja heidän tehtävänsä</saa:SaadosValiotsikkoKooste>
        <saa:Pykala saa1:pykalaLuokitusKoodi="Pykala" saa1:identifiointiTunnus="8 §">
          <saa:PykalaTunnusKooste>8 §</saa:PykalaTunnusKooste>
          <saa:KohdatMomentti>
            <saa:MomenttiJohdantoKooste>Ministeriössä voi olla</saa:MomenttiJohdantoKooste>
            <saa:MomenttiKohtaKooste>
kansliapäällikön sopimuspalkkainen virka sekä neuvottelevan virkamiehen, osastopäällikön, apulaisosastopäällikön, yli-insinöörin toimistopäällikkönä, toimistopäällikön, rakennusneuvoksen, yli-insinöörin, erikoistutkijan ja tutkijan sopimuspalkkaisia virkoja, sekä
</saa:MomenttiKohtaKooste>
            <saa:MomenttiKohtaKooste>
hallitusneuvoksen osastopäällikkönä, hallitusneuvoksen toimistopäällikkönä, hallitusneuvoksen, vanhemman ja nuoremman hallitussihteerin, yli-insinöörin, ylitarkastajan, tutkijan, taloussihteerin, tiedotuspäällikön, liikennetarkastajan, esittelijän, tiedotussihteerin, kielenkääntäjän, kansainvälisten asioiden sihteerin, tarkastajan, kamreerin, osastosihteerin, kirjaajan, ministerin sihteerin, toimistosihteerin, apulaiskirjaajan, pääkirjanpitäjän, ylivirastomestarin, toimistovirkailijan, virastomestarin, vahtimestarin, vahtimestari-autonkuljettajan, konekirjoittajan ja puhelunvälittäjän peruspalkkaisia virkoja.
</saa:MomenttiKohtaKooste>
            <saa:MomenttiKohtaKooste>
Lisäksi ministeriössä voi tulo- ja menoarvion rajoissa olla tilapäisiä virkamiehiä ja työsopimussuhteessa olevaa henkilöstöä.
</saa:MomenttiKohtaKooste>
          </saa:KohdatMomentti>
        </saa:Pykala>
        <saa:Pykala saa1:pykalaLuokitusKoodi="Pykala" saa1:identifiointiTunnus="9 §">
          <saa:PykalaTunnusKooste>9 §</saa:PykalaTunnusKooste>
          <saa:MomenttiKooste>Kelpoisuusvaatimuksena ministeriön virkoihin vaaditaan, että asianomainen on aikaisemmalla toiminnallaan osoittanut omaavansa sellaisen taidon ja kyvyn, jota viran menestyksellinen hoitaminen edellyttää.</saa:MomenttiKooste>
          <saa:KohdatMomentti>
            <saa:MomenttiJohdantoKooste>Lisäksi kelpoisuusvaatimuksena on:</saa:MomenttiJohdantoKooste>
            <saa:MomenttiKohtaKooste>
              <saa:MomenttiAlakohtaKooste>1) kansliapäälliköllä, osastopäälliköllä, apulaisosastopäälliköllä, toimistopäälliköllä, neuvottelevalla virkamiehellä, hallitusneuvoksella ja hallitussihteerillä mitä valtioneuvoston ohjesäännön 29§:n 1 momentissa, sellaisena kuin se on 4 päivänä joulukuuta 1987 annetussa asetuksessa (929/87), on säädetty. Sen lisäksi vaaditaan:</saa:MomenttiAlakohtaKooste>
              <saa:MomenttiAlakohtaKooste>
kansliapäälliköltä perehtyneisyyttä liikenne- ja viestintäasioihin;
</saa:MomenttiAlakohtaKooste>
              <saa:MomenttiAlakohtaKooste>
osastopäälliköltä, hallitusneuvokselta osastopäällikkönä ja apulaisosastopäälliköltä perehtyneisyyttä osaston toimialaan kuuluviin tehtäviin;
</saa:MomenttiAlakohtaKooste>
              <saa:MomenttiAlakohtaKooste>
toimistopäälliköltä, hallitusneuvokselta toimistopäällikkönä ja yli-insinööriltä toimistopäällikkönä perehtyneisyyttä toimiston toimialaan kuuluviin tehtäviin; sekä
</saa:MomenttiAlakohtaKooste>
              <saa:MomenttiAlakohtaKooste>
neuvottelevalta virkamieheltä hyvä perehtyneisyys viestintäasioihin;
</saa:MomenttiAlakohtaKooste>
            </saa:MomenttiKohtaKooste>
            <saa:MomenttiKohtaKooste>
2) yleiselle osastolle sijoitetulla yli-insinöörillä virkaan soveltuva diplomi-insinöörin tutkinto sekä hyvä perehtyneisyys tietoliikenteen teknisiin kysymyksiin;
</saa:MomenttiKohtaKooste>
            <saa:MomenttiKohtaKooste>
3) rakennusneuvoksella ja liikennetalousosastolle sijoitetulla yli-insinöörillä virkaan soveltuva diplomi-insinöörin tutkinto;
</saa:MomenttiKohtaKooste>
            <saa:MomenttiKohtaKooste>
4) tieliikenneosastolle sijoitetuista yli-insinööreistä toisella virkaan soveltuva diplomi-insinöörin tutkinto sekä hyvä perehtyneisyys autoteknisiin kysymyksiin ja toisella virkaan soveltuva diplomi-insinöörin tutkinto sekä hyvä perehtyneisyys tieliikenneturvallisuusasioihin;
</saa:MomenttiKohtaKooste>
            <saa:MomenttiKohtaKooste>
5) erikoistutkijalla virkaan soveltuva ylempi korkeakoulututkinto sekä perehtyneisyys liikennetaloudellisiin asioihin;
</saa:MomenttiKohtaKooste>
            <saa:MomenttiKohtaKooste>
6) ylitarkastajista yleiselle osastolle sijoitetulla ylitarkastajalla virkaan soveltuva korkeakoulututkinto ja perehtyneisyys viestintään, liikennetalousosastolle sijoitetulla ylitarkastajalla virkaan soveltuva korkeakoulututkinto ja perehtyneisyys liikenneoloihin ja taloudellisiin kysymyksiin sekä tieliikenneosastolle sijoitetulla ylitarkastajalla virkaan soveltuva korkeakoulututkinto ja virkaan kuuluvien tehtävien edellyttämä perehtyneisyys tieliikenteeseen, autoteknisiin kysymyksiin tai vaarallisten aineiden kuljetuksiin;
</saa:MomenttiKohtaKooste>
            <saa:MomenttiKohtaKooste>
7) taloussihteerillä virkaan soveltuva ylempi korkeakoulututkinto ja perehtyneisyys julkiseen taloushallintoon ja -suunnitteluun;
</saa:MomenttiKohtaKooste>
            <saa:MomenttiKohtaKooste>
8) tiedotuspäälliköllä ja tiedotussihteerillä virkaan soveltuva ylempi korkeakoulututkinto ja perehtyneisyys tiedotustoimintaan;
</saa:MomenttiKohtaKooste>
            <saa:MomenttiKohtaKooste>
9) tutkijalla, liikennetarkastajalla, tarkastajalla ja kamreerilla virkaan soveltuva korkeakoulututkinto sekä liikennetarkastajalla lisäksi perehtyneisyys tieliikenteeseen ja kamreerilla lisäksi kirjanpidon ja valtion tililaitoksen tuntemus;
</saa:MomenttiKohtaKooste>
            <saa:MomenttiKohtaKooste>
10) esittelijällä oikeustieteen kandidaatin tutkinto;
</saa:MomenttiKohtaKooste>
            <saa:MomenttiKohtaKooste>
11) kielenkääntäjällä virkaan soveltuva ylempi korkeakoulututkinto ja sellainen kielitaito, jota viran hoitaminen edellyttää;
</saa:MomenttiKohtaKooste>
            <saa:MomenttiKohtaKooste>
12) kansainvälisten asioiden sihteerillä virkaan soveltuva korkeakoulututkinto ja sellainen kielitaito, jota viran hoitaminen edellyttää;
</saa:MomenttiKohtaKooste>
            <saa:MomenttiKohtaKooste>
13) osastosihteerillä ja kirjaajalla varanotaarin tutkinto tai muu virkaan soveltuva korkeakoulututkinto; sekä
</saa:MomenttiKohtaKooste>
          </saa:KohdatMomentti>
          <saa:MomenttiKooste>14) ministerin sihteerillä ja pääkirjanpitäjällä virkaan soveltuva tutkinto.</saa:MomenttiKooste>
        </saa:Pykala>
        <saa:Pykala saa1:pykalaLuokitusKoodi="Pykala" saa1:identifiointiTunnus="10 §">
          <saa:PykalaTunnusKooste>10 §</saa:PykalaTunnusKooste>
          <saa:MomenttiKooste>Kansliapäällikön, neuvottelevan virkamiehen, osastopäällikön, hallitusneuvoksen osastopäällikkönä ja apulaisosastopäällikön nimittää tasavallan presidentti valtioneuvoston esityksestä virkaa haettavaksi julistamatta.</saa:MomenttiKooste>
          <saa:MomenttiKooste>Hallitusneuvoksen toimistopäällikkönä, yli-insinöörin toimistopäällikkönä, toimistopäällikön, hallitusneuvoksen, rakennusneuvoksen ja hallitussihteerin nimittää tasavallan presidentti valtioneuvoston esityksestä.</saa:MomenttiKooste>
          <saa:MomenttiKooste>Muut virat ja tilapäiset virat täyttää sekä työsopimussuhteessa olevan henkilöstön ottaa ministeriö.</saa:MomenttiKooste>
        </saa:Pykala>
        <saa:Pykala saa1:pykalaLuokitusKoodi="Pykala" saa1:identifiointiTunnus="11 §">
          <saa:PykalaTunnusKooste>11 § </saa:PykalaTunnusKooste>
          <sis:Katkoviiva/>
          <saa:MomenttiKooste>Sen lisäksi mitä valtioneuvoston ohjesäännön 33§:ssä on säädetty, kansliapäällikkö ratkaisee kirjaajan ja sitä alempien virkojen täyttämistä sekä niiden työsopimussuhteisten henkilöiden, joilta ei edellytetä korkeakoulututkintoa, työsuhteeseen ottamista ja irtisanomista koskevat asiat.</saa:MomenttiKooste>
        </saa:Pykala>
        <saa:Pykala saa1:pykalaLuokitusKoodi="Pykala" saa1:identifiointiTunnus="21 §">
          <saa:PykalaTunnusKooste>21 §</saa:PykalaTunnusKooste>
          <saa:MomenttiKooste>Tieliikenneosaston osastopäällikkö ratkaisee asiat, jotka koskevat ammattimaisen moottoriajoneuvoliikenteen ja kuljettajaopetustoiminnan harjoittamista.</saa:MomenttiKooste>
        </saa:Pykala>
        <saa:Pykala saa1:pykalaLuokitusKoodi="Pykala" saa1:identifiointiTunnus="22 §">
          <saa:PykalaTunnusKooste>22 §</saa:PykalaTunnusKooste>
          <saa:KohdatMomentti>
            <saa:MomenttiJohdantoKooste>Tieliikenneosaston teknillisen toimiston toimistopäällikkö ratkaisee asiat, jotka koskevat:</saa:MomenttiJohdantoKooste>
            <saa:MomenttiKohtaKooste>
1) rekisteröimättömän ajoneuvon käyttämistä liikenteessä;
</saa:MomenttiKohtaKooste>
            <saa:MomenttiKohtaKooste>
2) ajoneuvojen jaottelua ja siitä johtuvia erikoisohjeita; sekä
</saa:MomenttiKohtaKooste>
            <saa:MomenttiKohtaKooste>
3) ajoneuvojen rakenteeseen, varusteisiin, kytkentään ja kuormitukseen liittyviä lupia sekä poikkeuksia annetuista määräyksistä.
</saa:MomenttiKohtaKooste>
          </saa:KohdatMomentti>
        </saa:Pykala>
        <saa:Pykala saa1:pykalaLuokitusKoodi="Pykala" saa1:identifiointiTunnus="26 §">
          <saa:PykalaTunnusKooste>26 §</saa:PykalaTunnusKooste>
          <saa:MomenttiKooste>Sen estämättä, mitä 9§:ssä on säädetty kelpoisuusvaatimuksista, säilyttävät asetuksen voimaan tullessa ministeriön palveluksessa olevat viran tai ylimääräisen toimen haltijat kelpoisuutensa niihin virkoihin tai valtion virkamieslain voimaanpanolain (756/86) 9§:n nojalla peruspalkkaisiksi viroiksi muuttuviin ylimääräisiin toimiin, joita he tällöin hoitavat.</saa:MomenttiKooste>
        </saa:Pykala>
        <sis:Palstaviiva/>
        <saa:Pykala saa1:identifiointiTunnus="Voimaantulo" saa1:pykalaLuokitusKoodi="VoimaantuloSaannos">
          <saa:MomenttiKooste>Tämä asetus tulee voimaan 1 päivänä tammikuuta 1988.</saa:MomenttiKooste>
          <saa:MomenttiKooste>Ennen asetuksen voimaantuloa voidaan ryhtyä tarvittaviin toimenpiteisiin sen täytäntöönpanemiseksi.</saa:MomenttiKooste>
        </saa:Pykala>
      </saa:Pykalisto>
    </saa:Saados>
  </saa:SaadosOsa>
  <asi:AllekirjoitusOsa>
    <asi:PaivaysKooste>Helsingissä 18 päivänä joulukuuta 1987</asi:PaivaysKooste>
    <asi:Allekirjoittaja>
      <org:Henkilo>
        <org1:AsemaTeksti>Tasavallan Presidentti </org1:AsemaTeksti>
        <org1:SukuNimi>Mauno Koivisto</org1:SukuNimi>
      </org:Henkilo>
    </asi:Allekirjoittaja>
    <asi:Allekirjoittaja>
      <org:Henkilo>
        <org1:AsemaTeksti>Liikenneministeri </org1:AsemaTeksti>
        <org1:SukuNimi>Pekka Vennamo</org1:SukuNimi>
      </org:Henkilo>
    </asi:Allekirjoittaja>
  </asi:AllekirjoitusOsa>
</vah:VahvistettavaLaki>
