<?xml version="1.0" encoding="utf-8"?>
<vah:VahvistettavaLaki xmlns:vah="http://www.vn.fi/skeemat/vahvistettavalaki/2010/04/27" xmlns:sdk="http://www.finlex.fi/skeemat/edita/sdk/2010/04/27" xmlns:saa="http://www.vn.fi/skeemat/saadoskooste/2010/04/27" xmlns:saa1="http://www.vn.fi/skeemat/saadoselementit/2010/04/27" xmlns:met="http://www.vn.fi/skeemat/metatietokooste/2010/04/27" xmlns:met1="http://www.vn.fi/skeemat/metatietoelementit/2010/04/27" xmlns:asi="http://www.vn.fi/skeemat/asiakirjakooste/2010/04/27" xmlns:asi1="http://www.vn.fi/skeemat/asiakirjaelementit/2010/04/27" xmlns:org="http://www.vn.fi/skeemat/organisaatiokooste/2010/02/15" xmlns:org1="http://www.vn.fi/skeemat/organisaatioelementit/2010/02/15" xmlns:tau="http://www.vn.fi/skeemat/taulukkokooste/2010/04/27" xmlns:sis="http://www.vn.fi/skeemat/sisaltokooste/2010/04/27" xmlns:sis1="http://www.vn.fi/skeemat/sisaltoelementit/2010/04/27" met1:kieliKoodi="fi" met1:julkisuusKoodi="julkinen" met1:tilaKoodi="Valmis" met1:identifiointiTunnus="0000000000000000" met1:versioTeksti="1.0" met1:asiakirjatyyppiNimi="Vahvistettava laki" met1:laadintaPvm="1998-03-18" met1:rakennemaarittelyNimi="vahvistettavalaki.xsd">
  <asi:IdentifiointiOsa>
    <met1:AsiakirjatyyppiNimi>Vahvistettava laki</met1:AsiakirjatyyppiNimi>
    <asi:EduskuntaTunniste>
      <met1:AsiakirjatyyppiKoodi>SDK</met1:AsiakirjatyyppiKoodi>
      <asi1:AsiakirjaNroTeksti>183</asi1:AsiakirjaNroTeksti>
      <asi1:ValtiopaivavuosiTeksti>1998</asi1:ValtiopaivavuosiTeksti>
    </asi:EduskuntaTunniste>
    <met:Nimeke>
      <met1:NimekeTeksti>poliisin hallinnosta annetun asetuksen muuttamisesta</met1:NimekeTeksti>
    </met:Nimeke>
  </asi:IdentifiointiOsa>
  <saa:SaadosOsa>
    <saa:Saados met1:kieliKoodi="fi" saa1:saadostyyppiNimi="Asetus">
      <saa:SaadosNimeke>
        <saa:SaadostyyppiKooste>Asetus</saa:SaadostyyppiKooste>
        <saa:SaadosNimekeKooste>poliisin hallinnosta annetun asetuksen muuttamisesta</saa:SaadosNimekeKooste>
      </saa:SaadosNimeke>
      <saa:Johtolause>
        <saa:SaadosKappaleKooste>Sisäasiainministerin esittelystä</saa:SaadosKappaleKooste>
        <saa:SaadosKappaleKooste><saa:SaadosKursiiviKooste> muutetaan</saa:SaadosKursiiviKooste> poliisin hallinnosta 15 päivänä maaliskuuta 1996 annetun asetuksen (158/1996) 5 §, 7 §:n 2 momentti, 8―10 §, 16 §, 17 §:n 1 momentti, 21 §:n 2 ja 3 momentti, 22 §:n 3 momentti, 23 §:n 1 momentti, 26 §:n 2 momentti, 27 §, 28 §:n 2 momentti sekä 30 ja 31 §,</saa:SaadosKappaleKooste>
        <saa:SaadosKappaleKooste>sellaisina kuin niistä ovat 16 § ja 17 §:n 1 momentti asetuksessa 1273/1997 ja 30 §:n 2 momentti asetuksessa 487/1997, seuraavasti:</saa:SaadosKappaleKooste>
      </saa:Johtolause>
      <saa:Pykalisto>
        <saa:Pykala saa1:pykalaLuokitusKoodi="Pykala" saa1:identifiointiTunnus="5 §">
          <saa:PykalaTunnusKooste>5 §</saa:PykalaTunnusKooste>
          <saa:KohdatMomentti>
            <saa:MomenttiJohdantoKooste>Helsingin poliisilaitos hoitaa suoraan ministeriön alaisena tehtävät, jotka koskevat:</saa:MomenttiJohdantoKooste>
            <saa:MomenttiKohtaKooste>
1) poliisilaitoksen tulossuunnitelmaa ja talousarviota;
</saa:MomenttiKohtaKooste>
            <saa:MomenttiKohtaKooste>
2) valtakunnallisia erityistehtäviä; sekä
</saa:MomenttiKohtaKooste>
            <saa:MomenttiKohtaKooste>
3) poliisilaitoksen henkilöstöä ja poliisisoittokuntaa.
</saa:MomenttiKohtaKooste>
          </saa:KohdatMomentti>
        </saa:Pykala>
        <saa:Pykala saa1:pykalaLuokitusKoodi="Pykala" saa1:identifiointiTunnus="7 §">
          <saa:PykalaTunnusKooste>7 §</saa:PykalaTunnusKooste>
          <sis:Katkoviiva/>
          <saa:MomenttiKooste>Ministeriö vahvistaa keskusrikospoliisin alueyksikköjen toimialueet.</saa:MomenttiKooste>
        </saa:Pykala>
        <saa:Pykala saa1:pykalaLuokitusKoodi="Pykala" saa1:identifiointiTunnus="8 §">
          <saa:PykalaTunnusKooste>8 §</saa:PykalaTunnusKooste>
          <saa:MomenttiKooste>Suojelupoliisin tulee poliisin hallinnosta annetussa laissa säädetyn tehtävän toteuttamiseksi antaa ministeriön vahvistamien yleisten perusteiden mukaisesti viranomaisille ja yhteisöille sellaisia ohjeita, neuvoja ja tietoja, jotka ovat tarpeen valtion turvallisuuden ylläpitämiseksi tai siihen kohdistuvien loukkausten estämiseksi.</saa:MomenttiKooste>
          <saa:MomenttiKooste>Ministeriö vahvistaa suojelupoliisin alueyksikköjen toimialueet.</saa:MomenttiKooste>
        </saa:Pykala>
        <saa:Pykala saa1:pykalaLuokitusKoodi="Pykala" saa1:identifiointiTunnus="9 §">
          <saa:PykalaTunnusKooste>9 §</saa:PykalaTunnusKooste>
          <saa:KohdatMomentti>
            <saa:MomenttiJohdantoKooste>Liikkuvan poliisin tulee poliisin hallinnosta annetussa laissa säädettyjen tehtävien toteuttamiseksi erityisesti:</saa:MomenttiJohdantoKooste>
            <saa:MomenttiKohtaKooste>
1) seurata liikenneturvallisuuskehitystä sekä kehittää liikennevalvontamenetelmiä ja yhteistyössä Poliisin tekniikkakeskuksen kanssa liikennevalvonnassa käytettäviä välineitä;
</saa:MomenttiKohtaKooste>
            <saa:MomenttiKohtaKooste>
2) suorittaa ajoneuvoihin ja niiden kuljettajiin kohdistuvaa valvontaa päätieverkolla;
</saa:MomenttiKohtaKooste>
            <saa:MomenttiKohtaKooste>
3) suorittaa raskaan liikenteen valvontaa;
</saa:MomenttiKohtaKooste>
            <saa:MomenttiKohtaKooste>
4) huolehtia EY:n säädöksissä edellytetystä vaarallisten aineiden kuljetusten sekä kuljettajien ajo- ja lepoaikojen valvonnasta;
</saa:MomenttiKohtaKooste>
            <saa:MomenttiKohtaKooste>
5) suorittaa maastoliikenteen ja vesiliikenteen valvontaa;
</saa:MomenttiKohtaKooste>
            <saa:MomenttiKohtaKooste>
6) suorittaa sen hoidettavaksi säädetyt ja määrätyt erityisturvatehtävät;
</saa:MomenttiKohtaKooste>
            <saa:MomenttiKohtaKooste>
7) suorittaa sen vastuulle annetut poliisin ajokoulutustehtävät.
</saa:MomenttiKohtaKooste>
          </saa:KohdatMomentti>
          <saa:MomenttiKooste>Ministeriö vahvistaa liikkuvan poliisin alueyksikköjen toimialueet.</saa:MomenttiKooste>
        </saa:Pykala>
        <saa:Pykala saa1:pykalaLuokitusKoodi="Pykala" saa1:identifiointiTunnus="10 §">
          <saa:PykalaTunnusKooste>10 §</saa:PykalaTunnusKooste>
          <saa:MomenttiKooste>Ministeriön yhteydessä toimii poliisiasiain neuvottelukunta ja poliisilaitoksen yhteydessä poliisin neuvottelukunta. Lääninhallitus tai ministeriö voi poliisin hallinnosta annetun lain 3 §:n 1 momentin nojalla päättää, että yhteistoiminta-alueella toimii yhteistoiminta-alueen neuvottelukunta.</saa:MomenttiKooste>
        </saa:Pykala>
        <saa:Pykala saa1:pykalaLuokitusKoodi="Pykala" saa1:identifiointiTunnus="16 §">
          <saa:PykalaTunnusKooste>16 §</saa:PykalaTunnusKooste>
          <saa:KohdatMomentti>
            <saa:MomenttiJohdantoKooste>Kelpoisuusvaatimuksena poliisin virkoihin on:</saa:MomenttiJohdantoKooste>
            <saa:MomenttiKohtaKooste>
1) keskusrikospoliisin päälliköllä oikeustieteen kandidaatin tutkinto tai poliisipäällystön tutkinnon lisäksi poliisikoulutuksesta annetun asetuksen 23 §:ssä tarkoitettu ylempi korkeakoulututkinto, perehtyneisyys hallinnonalan toimintaan ja tehtäväalueeseen sekä käytännössä osoitettu johtamistaito ja johtamiskokemus;
</saa:MomenttiKohtaKooste>
            <saa:MomenttiKohtaKooste>
2) suojelupoliisin päälliköllä oikeustieteen kandidaatin tutkinto tai poliisipäällystön tutkinnon lisäksi poliisikoulutuksesta annetun asetuksen 23 §:ssä tarkoitettu ylempi korkeakoulututkinto, perehtyneisyys hallinnonalan toimintaan sekä käytännössä osoitettu johtamistaito ja johtamiskokemus;
</saa:MomenttiKohtaKooste>
            <saa:MomenttiKohtaKooste>
3) liikkuvan poliisin päälliköllä oikeustieteen kandidaatin tutkinto tai poliisipäällystön tutkinnon lisäksi poliisikoulutuksesta annetun asetuksen 23 §:ssä tarkoitettu ylempi korkeakoulututkinto, perehtyneisyys hallinnonalan toimintaan ja tehtäväalueeseen sekä käytännössä osoitettu johtamistaito ja johtamiskokemus;
</saa:MomenttiKohtaKooste>
            <saa:MomenttiKohtaKooste>
4) liikkuvan poliisin apulaispäälliköllä ylempi korkeakoulututkinto ja perehtyneisyys tehtäväalueeseen taikka poliisipäällystön tutkinto;
</saa:MomenttiKohtaKooste>
            <saa:MomenttiKohtaKooste>
5) keskusrikospoliisin apulaispäälliköllä sekä Tampereen ja Turun kihlakunnan poliisilaitoksen hallinto-osaston johtajalla oikeustieteen kandidaatin tutkinto tai poliisipäällystön tutkinnon lisäksi poliisikoulutuksesta annetun asetuksen 23 §:ssä tarkoitettu ylempi korkeakoulututkinto;
</saa:MomenttiKohtaKooste>
            <saa:MomenttiKohtaKooste>
6) rikosylitarkastajalla ja rikostarkastajalla ylempi korkeakoulututkinto tai ekonomin tutkinto sekä perehtyneisyys tehtäväalueeseen tai poliisipäällystön tutkinto;
</saa:MomenttiKohtaKooste>
            <saa:MomenttiKohtaKooste>
7) apulaispoliisipäälliköllä tehtävien laadun mukaan joko oikeustieteen kandidaatin tutkinto tai poliisipäällystön tutkinto sekä perehtyneisyys tehtäväalueeseen;
</saa:MomenttiKohtaKooste>
            <saa:MomenttiKohtaKooste>
8) keskusrikospoliisin osastopäälliköllä, suojelupoliisin osastopäälliköllä sekä keskusrikospoliisin laboratorion johtajalla ylempi korkeakoulututkinto ja perehtyneisyys tehtäväalueeseen;
</saa:MomenttiKohtaKooste>
            <saa:MomenttiKohtaKooste>
9) Poliisin tekniikkakeskuksen johtajalla diplomi-insinöörin tutkinto tai insinöörin tutkinto sekä perehtyneisyys tehtäväalueeseen ja käytännössä osoitettu johtamistaito;
</saa:MomenttiKohtaKooste>
            <saa:MomenttiKohtaKooste>
10) keskusrikospoliisin rikoskemistillä, rikosinsinöörillä ja tutkijalla ylempi korkeakoulututkinto;
</saa:MomenttiKohtaKooste>
            <saa:MomenttiKohtaKooste>
11) muilla päällystöön kuuluvilla poliisimiehillä poliisipäällystön tutkinto tai korkeakoulututkinto sekä perehtyneisyys tehtäväalueeseen;
</saa:MomenttiKohtaKooste>
            <saa:MomenttiKohtaKooste>
12) alipäällystöön kuuluvilla poliisimiehillä poliisialipäällystön tutkinto tai korkeakoulututkinto sekä perehtyneisyys tehtäväalueeseen;
</saa:MomenttiKohtaKooste>
            <saa:MomenttiKohtaKooste>
13) nuoremmalla konstaapelilla poliisin perustutkinnon perusopinnot 1:n suorittaminen tai kokelaskurssi;
</saa:MomenttiKohtaKooste>
            <saa:MomenttiKohtaKooste>
14) muulla miehistöön kuuluvalla poliisimiehellä poliisin perustutkinto tai poliisimiehistön virkatutkinto.
</saa:MomenttiKohtaKooste>
          </saa:KohdatMomentti>
        </saa:Pykala>
        <saa:Pykala saa1:pykalaLuokitusKoodi="Pykala" saa1:identifiointiTunnus="17 §">
          <saa:PykalaTunnusKooste>17 §</saa:PykalaTunnusKooste>
          <saa:MomenttiKooste>Keskusrikospoliisin päällikön, suojelupoliisin päällikön ja liikkuvan poliisin päällikön nimittää tasavallan presidentti valtioneuvoston esityksestä.</saa:MomenttiKooste>
          <sis:Katkoviiva/>
        </saa:Pykala>
        <saa:Pykala saa1:pykalaLuokitusKoodi="Pykala" saa1:identifiointiTunnus="21 §">
          <saa:PykalaTunnusKooste>21 §</saa:PykalaTunnusKooste>
          <sis:Katkoviiva/>
          <saa:MomenttiKooste>Valtioneuvosto myöntää virkavapauden 17 §:n 1 momentissa mainitulle virkamiehelle. Ministeriö myöntää kuitenkin 17 §:n 1 momentissa mainitulle virkamiehelle virkavapauden, jonka saamiseen virkamiehellä on lain tai virkaehtosopimuksen nojalla oikeus, ja muun virkavapauden, joka kestää enintään vuoden.</saa:MomenttiKooste>
          <saa:MomenttiKooste>Poliisilaitos myöntää virkavapauden myös ministeriön tai lääninhallituksen nimittämälle alaiselleen virkamiehelle silloin, kun kyse on virkavapaudesta, jonka saamiseen virkamiehellä on lain tai virkaehtosopimuksen nojalla oikeus, ja muun virkavapauden, joka kestää enintään vuoden.</saa:MomenttiKooste>
        </saa:Pykala>
        <saa:Pykala saa1:pykalaLuokitusKoodi="Pykala" saa1:identifiointiTunnus="22 §">
          <saa:PykalaTunnusKooste>22 §</saa:PykalaTunnusKooste>
          <sis:Katkoviiva/>
          <saa:MomenttiKooste>Edellä 17 §:n 1 momentissa tarkoitetun virkamiehen nimittää määräaikaiseen virkasuhteeseen enintään vuodeksi ministeriö ja yli vuodeksi valtioneuvosto.</saa:MomenttiKooste>
        </saa:Pykala>
        <saa:Pykala saa1:pykalaLuokitusKoodi="Pykala" saa1:identifiointiTunnus="23 §">
          <saa:PykalaTunnusKooste>23 §</saa:PykalaTunnusKooste>
          <saa:MomenttiKooste>Sivutoimiluvan myöntää nimittävä viranomainen. Edellä 17 §:n 1 momentissa mainitulle virkamiehelle sivutoimiluvan myöntää kuitenkin ministeriö.</saa:MomenttiKooste>
          <sis:Katkoviiva/>
        </saa:Pykala>
        <saa:Pykala saa1:pykalaLuokitusKoodi="Pykala" saa1:identifiointiTunnus="26 §">
          <saa:PykalaTunnusKooste>26 §</saa:PykalaTunnusKooste>
          <sis:Katkoviiva/>
          <saa:MomenttiKooste>Valtion virkamieslain 27 §:n nojalla virkamiehen irtisanoo asianomainen virasto. Edellä 17 §:n 1 momentissa mainitun virkamiehen irtisanoo kuitenkin ministeriö. Nimismiehen ja poliisipäällikön sekä 17 §:n 2 momentissa mainitun viraston päällikön irtisanoo nimittävä viranomainen.</saa:MomenttiKooste>
        </saa:Pykala>
        <saa:Pykala saa1:pykalaLuokitusKoodi="Pykala" saa1:identifiointiTunnus="27 §">
          <saa:PykalaTunnusKooste>27 §</saa:PykalaTunnusKooste>
          <saa:MomenttiKooste>Virkamiehelle annettavasta varoituksesta, lomauttamisesta ja virkasuhteen muuttamisesta osa-aikaiseksi päättää nimittävä viranomainen. Edellä 17 §:n 1 momentissa tarkoitetun virkamiehen osalta päätöksen tekee kuitenkin ministeriö.</saa:MomenttiKooste>
        </saa:Pykala>
        <saa:Pykala saa1:pykalaLuokitusKoodi="Pykala" saa1:identifiointiTunnus="28 §">
          <saa:PykalaTunnusKooste>28 §</saa:PykalaTunnusKooste>
          <sis:Katkoviiva/>
          <saa:MomenttiKooste>Yhteistoiminta-alueen ohjesäännön vahvistaa poliisin lääninjohto. Poliisin hallinnosta annetun lain 8 §:n 3 momentissa tarkoitetussa tapauksessa ohjesäännön vahvistaa ministeriö.</saa:MomenttiKooste>
          <sis:Katkoviiva/>
        </saa:Pykala>
        <saa:Pykala saa1:pykalaLuokitusKoodi="Pykala" saa1:identifiointiTunnus="30 §">
          <saa:PykalaTunnusKooste>30 §</saa:PykalaTunnusKooste>
          <saa:MomenttiKooste>Helsingin poliisilaitoksen poliisipäälliköllä on poliisikomentajan arvonimi. Keskusrikospoliisin, suojelupoliisin ja liikkuvan poliisin päälliköllä on poliisineuvoksen arvonimi.</saa:MomenttiKooste>
          <saa:MomenttiKooste>Marraskuun 30 päivänä 1996 nimismiehen ja apulaisnimismiehen vakinaisessa virassa ollut virkamies voi käyttää nimismiehen arvonimeä ja mainittuna ajankohtana poliisi mestarin ja apulaispoliisimestarin vakinaises-sa virassa ollut virkamies poliisimestarin arvonimeä niin kauan kuin hän on kihlakunnanviraston tai kihlakunnan erillisen viraston poliisipäällikön, apulaispoliisipäällikön, johtavan kihlakunnanvoudin, kihlakunnanvoudin, johtavan kihlakunnansyyttäjän tai kihlakunnansyyttäjän virassa sekä näistä vi-roista eläkkeelle jäätyään.</saa:MomenttiKooste>
        </saa:Pykala>
        <saa:Pykala saa1:pykalaLuokitusKoodi="Pykala" saa1:identifiointiTunnus="31 §">
          <saa:PykalaTunnusKooste>31 §</saa:PykalaTunnusKooste>
          <saa:MomenttiKooste>Suojelupoliisin päällikköä, keskusrikospo-liisin päällikköä, liikkuvan poliisin päällikköä ja nimismiestä sekä poliisipäällikköä syytetään virkarikoksesta hovioikeudessa.</saa:MomenttiKooste>
        </saa:Pykala>
        <sis:Palstaviiva/>
        <saa:Pykala saa1:identifiointiTunnus="Voimaantulo" saa1:pykalaLuokitusKoodi="VoimaantuloSaannos">
          <saa:MomenttiKooste>Tämä asetus tulee voimaan 1 päivänä huhtikuuta 1998.</saa:MomenttiKooste>
          <saa:MomenttiKooste>Ennen asetuksen voimaantuloa voidaan ryhtyä asetuksen täytäntöönpanon edellyttämiin toimenpiteisiin.</saa:MomenttiKooste>
        </saa:Pykala>
      </saa:Pykalisto>
    </saa:Saados>
  </saa:SaadosOsa>
  <asi:AllekirjoitusOsa>
    <asi:PaivaysKooste>Helsingissä 13 päivänä maaliskuuta 1998</asi:PaivaysKooste>
    <asi:Allekirjoittaja>
      <org:Henkilo>
        <org1:AsemaTeksti>Tasavallan Presidentti </org1:AsemaTeksti>
        <org1:SukuNimi>MARTTI AHTISAARI</org1:SukuNimi>
      </org:Henkilo>
    </asi:Allekirjoittaja>
    <asi:Allekirjoittaja>
      <org:Henkilo>
        <org1:AsemaTeksti>Sisäasiainministeri </org1:AsemaTeksti>
        <org1:SukuNimi>Jan-Erik Enestam </org1:SukuNimi>
      </org:Henkilo>
    </asi:Allekirjoittaja>
  </asi:AllekirjoitusOsa>
</vah:VahvistettavaLaki>
