<?xml version="1.0" encoding="utf-8"?>
<vah:VahvistettavaLaki xmlns:vah="http://www.vn.fi/skeemat/vahvistettavalaki/2010/04/27" xmlns:sdk="http://www.finlex.fi/skeemat/edita/sdk/2010/04/27" xmlns:saa="http://www.vn.fi/skeemat/saadoskooste/2010/04/27" xmlns:saa1="http://www.vn.fi/skeemat/saadoselementit/2010/04/27" xmlns:met="http://www.vn.fi/skeemat/metatietokooste/2010/04/27" xmlns:met1="http://www.vn.fi/skeemat/metatietoelementit/2010/04/27" xmlns:asi="http://www.vn.fi/skeemat/asiakirjakooste/2010/04/27" xmlns:asi1="http://www.vn.fi/skeemat/asiakirjaelementit/2010/04/27" xmlns:org="http://www.vn.fi/skeemat/organisaatiokooste/2010/02/15" xmlns:org1="http://www.vn.fi/skeemat/organisaatioelementit/2010/02/15" xmlns:tau="http://www.vn.fi/skeemat/taulukkokooste/2010/04/27" xmlns:sis="http://www.vn.fi/skeemat/sisaltokooste/2010/04/27" xmlns:sis1="http://www.vn.fi/skeemat/sisaltoelementit/2010/04/27" met1:kieliKoodi="sv" met1:julkisuusKoodi="julkinen" met1:tilaKoodi="Valmis" met1:identifiointiTunnus="0000000000000000" met1:versioTeksti="1.0" met1:asiakirjatyyppiNimi="Vahvistettava laki" met1:laadintaPvm="2100-01-01" met1:rakennemaarittelyNimi="vahvistettavalaki.xsd">
  <asi:IdentifiointiOsa>
    <met1:AsiakirjatyyppiNimi>Vahvistettava laki</met1:AsiakirjatyyppiNimi>
    <asi:EduskuntaTunniste>
      <met1:AsiakirjatyyppiKoodi>SDK</met1:AsiakirjatyyppiKoodi>
      <asi1:AsiakirjaNroTeksti>781</asi1:AsiakirjaNroTeksti>
      <asi1:ValtiopaivavuosiTeksti>2018</asi1:ValtiopaivavuosiTeksti>
    </asi:EduskuntaTunniste>
    <met:Nimeke>
      <met1:NimekeTeksti>om ändring av statsrådets förordning om avstjälpningsplatser</met1:NimekeTeksti>
    </met:Nimeke>
    <met:AsiakirjaViitteet>
      <met:Muu1Viite>
        <sis1:ViiteTeksti>Europaparlamentets och rådets förordning (EU) 2017/852 (32017R0852); EUT nr L 137, 24.5.2017, s. 1</sis1:ViiteTeksti>
      </met:Muu1Viite>
    </met:AsiakirjaViitteet>
  </asi:IdentifiointiOsa>
  <saa:SaadosOsa>
    <saa:Saados met1:kieliKoodi="sv" saa1:saadostyyppiNimi="Asetus">
      <saa:SaadosNimeke>
        <saa:SaadostyyppiKooste>Statsrådets förordning</saa:SaadostyyppiKooste>
        <saa:SaadosNimekeKooste>om ändring av statsrådets förordning om avstjälpningsplatser</saa:SaadosNimekeKooste>
      </saa:SaadosNimeke>
      <saa:Johtolause>
        <saa:SaadosKappaleKooste>I enlighet med statsrådets beslut</saa:SaadosKappaleKooste>
        <saa:SaadosKappaleKooste><saa:SaadosKursiiviKooste>ändras</saa:SaadosKursiiviKooste> i statsrådets förordning om avstjälpningsplatser (331/2013) 3 § 12 punkten, 10 §, 14 § 2 mom., 37, 48 och 51 § samt bilaga 4 till förordningen, samt</saa:SaadosKappaleKooste>
        <saa:SaadosKappaleKooste><saa:SaadosKursiiviKooste>fogas</saa:SaadosKursiiviKooste> till 3 § en ny 13 punkt som följer:</saa:SaadosKappaleKooste>
      </saa:Johtolause>
      <saa:Pykalisto>
        <saa:Pykala saa1:pykalaLuokitusKoodi="Pykala" saa1:identifiointiTunnus="3 §">
          <saa:PykalaTunnusKooste>3 §</saa:PykalaTunnusKooste>
          <saa:SaadosOtsikkoKooste>Definitioner</saa:SaadosOtsikkoKooste>
          <saa:KohdatMomentti>
            <saa:MomenttiJohdantoKooste>I denna förordning avses med</saa:MomenttiJohdantoKooste>
            <sis:Katkoviiva/>
            <saa:MomenttiKohtaKooste>12) <saa:SaadosKursiiviKooste>efterbehandling av avstjälpningsplatser</saa:SaadosKursiiviKooste> åtgärder som vidtas för uppföljning eller bekämpning av miljöpåverkan från en avstjälpningsplats som ska läggas ned eller har lagts ned,</saa:MomenttiKohtaKooste>
            <saa:MomenttiKohtaKooste>13) <saa:SaadosKursiiviKooste>kvicksilveravfall</saa:SaadosKursiiviKooste> metalliskt kvicksilver som enligt Europaparlamentets och rådets förordning (EU) 2017/852 om kvicksilver och om upphävande av förordning (EG) nr 1102/2008, nedan <saa:SaadosKursiiviKooste>kvicksilverförordningen</saa:SaadosKursiiviKooste>, betraktas som avfall.</saa:MomenttiKohtaKooste>
          </saa:KohdatMomentti>
        </saa:Pykala>
        <saa:Pykala saa1:pykalaLuokitusKoodi="Pykala" saa1:identifiointiTunnus="10 §">
          <saa:PykalaTunnusKooste>10 §</saa:PykalaTunnusKooste>
          <saa:SaadosOtsikkoKooste>Tillfällig lagringsplats för kvicksilveravfall</saa:SaadosOtsikkoKooste>
          <saa:KohdatMomentti>
            <saa:MomenttiJohdantoKooste>Vid tillfällig lagring av kvicksilveravfall i mer än ett år i deponier på markytan ska följande krav iakttas:</saa:MomenttiJohdantoKooste>
            <saa:MomenttiKohtaKooste>1) kvicksilveravfall ska lagras åtskilt från annat avfall,</saa:MomenttiKohtaKooste>
            <saa:MomenttiKohtaKooste>2) behållarna ska lagras i uppsamlingsbassänger som är försedda med lämplig beläggning som gör att de saknar sprickor och hål och är ogenomträngliga för kvicksilveravfall och de ska ha en tillräckligt stor volym för den lagrade kvantiteten kvicksilver,</saa:MomenttiKohtaKooste>
            <saa:MomenttiKohtaKooste>3) lagringsplatsen ska vara försedd med konstruerade eller naturliga barriärer som klarar av att skydda miljön från kvicksilverutsläpp, och den ska ha en tillräckligt stor volym för den totala lagrade kvantiteten kvicksilver,</saa:MomenttiKohtaKooste>
            <saa:MomenttiKohtaKooste>4) lagringsplatsens golv ska vara täckt av ett material som är kvicksilverbeständigt och det ska finnas en lutning mot en uppsamlingsbrunn,</saa:MomenttiKohtaKooste>
            <saa:MomenttiKohtaKooste>5) lagringsplatsen ska vara utrustad med ett brandskyddssystem,</saa:MomenttiKohtaKooste>
            <saa:MomenttiKohtaKooste>6) lagringen ska organiseras på ett sådant sätt att det säkerställs att alla behållare är lätt åtkomliga.</saa:MomenttiKohtaKooste>
          </saa:KohdatMomentti>
          <saa:MomenttiKooste>Kraven i 1 mom. 3 och 5 punkten ska iakttas också i deponier för bortskaffande av kvicksilveravfall på eller och under markytan.</saa:MomenttiKooste>
        </saa:Pykala>
        <saa:Pykala saa1:pykalaLuokitusKoodi="Pykala" saa1:identifiointiTunnus="14 §">
          <saa:PykalaTunnusKooste>14 §</saa:PykalaTunnusKooste>
          <saa:SaadosOtsikkoKooste>Avfall som inte tas emot på avstjälpningsplatser</saa:SaadosOtsikkoKooste>
          <sis:Katkoviiva/>
          <saa:MomenttiKooste>Bestämmelserna i 1 mom. 1 punkten tillämpas dock inte på sådant kvicksilveravfall vars tillfälliga lagring är tillåten med stöd av artikel 13 i kvicksilverförordningen eller bestämmelser som har utfärdats med stöd av den.</saa:MomenttiKooste>
          <sis:Katkoviiva/>
        </saa:Pykala>
        <saa:Pykala saa1:pykalaLuokitusKoodi="Pykala" saa1:identifiointiTunnus="37 §">
          <saa:PykalaTunnusKooste>37 §</saa:PykalaTunnusKooste>
          <saa:SaadosOtsikkoKooste>Särskilda krav som gäller godkännande av kvicksilveravfall för tillfällig lagring och bortskaffande</saa:SaadosOtsikkoKooste>
          <saa:MomenttiKooste>Bestämmelser om undantag från tillämpningen av mottagningskriterierna enligt 32 § på kvicksilveravfall som lagras och bortskaffas på markytan samt om undantag från tillämpningen av mottagningskriterierna enligt 33 § på kvicksilveravfall som bortskaffas i deponier under markytan finns i artikel 13 i kvicksilverförordningen.</saa:MomenttiKooste>
          <saa:MomenttiKooste>Vid godkännande av kvicksilveravfall för tillfällig lagring och bortskaffande ska dessutom de krav som anges i bilaga 4 iakttas.</saa:MomenttiKooste>
        </saa:Pykala>
        <saa:Pykala saa1:pykalaLuokitusKoodi="Pykala" saa1:identifiointiTunnus="48 §">
          <saa:PykalaTunnusKooste>48 §</saa:PykalaTunnusKooste>
          <saa:SaadosOtsikkoKooste>Särskilda uppföljnings- och kontrollkrav som gäller tillfällig lagring av kvicksilveravfall</saa:SaadosOtsikkoKooste>
          <saa:KohdatMomentti>
            <saa:MomenttiJohdantoKooste>Vid tillfällig lagring av kvicksilveravfall i mer än ett år i deponier på markytan ska dessutom följande särskilda uppföljnings- och kontrollkrav iakttas:</saa:MomenttiJohdantoKooste>
            <saa:MomenttiKohtaKooste>
              <saa:MomenttiAlakohtaKooste>1) på lagringsplatsen ska det för övervakning av kvicksilverångor finnas ett kontinuerligt system,</saa:MomenttiAlakohtaKooste>
              <saa:MomenttiAlakohtaKooste>a) med en känslighet på minst 0,02 milligram kvicksilver i en kubikmeter luft,</saa:MomenttiAlakohtaKooste>
              <saa:MomenttiAlakohtaKooste>b) med sensorer på marknivå och i huvudhöjd,</saa:MomenttiAlakohtaKooste>
              <saa:MomenttiAlakohtaKooste>c) med ett visuellt och akustiskt varningssystem,</saa:MomenttiAlakohtaKooste>
              <saa:MomenttiAlakohtaKooste>d) som ska underhållas varje år,</saa:MomenttiAlakohtaKooste>
            </saa:MomenttiKohtaKooste>
            <saa:MomenttiKohtaKooste>2) lagringsplatsen och behållarna ska minst en gång i månaden besiktigas okulärt av den ansvariga personen för lagringsplatsen,</saa:MomenttiKohtaKooste>
            <saa:MomenttiKohtaKooste>3) på lagringsplatsen ska det omedelbart vidtas åtgärder som är nödvändiga för att förhindra alla utsläpp av kvicksilver i miljön och återställa en säker lagring av kvicksilver, om läckor upptäcks,</saa:MomenttiKohtaKooste>
            <saa:MomenttiKohtaKooste>4) tillsynsmyndigheten ska omedelbart underrättas om alla läckor,</saa:MomenttiKohtaKooste>
            <saa:MomenttiKohtaKooste>5) en beredskapsplan för nödsituationer ska utarbetas för lagringsplatsen och skyddsutrustning som är lämplig för hantering av kvicksilveravfall ska finnas tillgänglig på lagringsplatsen.</saa:MomenttiKohtaKooste>
          </saa:KohdatMomentti>
          <saa:MomenttiKooste>Huvudmannen ska arkivera alla dokument som innehåller den information som avses i 1 mom. och i bilaga 4 i minst tre år efter det att den tillfälliga lagringen upphört. Alla uppgifter om lageruttag av kvicksilveravfall, transport av kvicksilveravfall någon annanstans efter den tillfälliga lagringen och om dess destination och den planerade behandlingen av kvicksilveravfall ska även arkiveras.</saa:MomenttiKooste>
        </saa:Pykala>
        <saa:Pykala saa1:pykalaLuokitusKoodi="Pykala" saa1:identifiointiTunnus="51 §">
          <saa:PykalaTunnusKooste>51 §</saa:PykalaTunnusKooste>
          <saa:SaadosOtsikkoKooste>Uppgifter om genomförandet</saa:SaadosOtsikkoKooste>
          <saa:MomenttiKooste>Finlands miljöcentral ska vart tredje år, i enlighet med artikel 5 i rådets direktiv 91/692/EEG om att standardisera och rationalisera rapporteringen om genomförandet av vissa direktiv om miljön, lämna en rapport till Europeiska kommissionen om genomförandet i Finland av rådets direktiv 1999/31/EG om deponering av avfall. Finlands miljöcentral ska dessutom se till att uppgifter om de undantag som avses i 36 § lämnas till Europeiska kommissionen och till de andra medlemsstaterna i Europeiska unionen.</saa:MomenttiKooste>
        </saa:Pykala>
        <sis:Palstaviiva/>
        <saa:Pykala saa1:identifiointiTunnus="Voimaantulo" saa1:pykalaLuokitusKoodi="VoimaantuloSaannos">
          <saa:MomenttiKooste>Denna förordning träder i kraft den 15 september 2018.</saa:MomenttiKooste>
        </saa:Pykala>
      </saa:Pykalisto>
    </saa:Saados>
  </saa:SaadosOsa>
  <asi:AllekirjoitusOsa>
    <asi:PaivaysKooste>Helsingfors den 6 september 2018</asi:PaivaysKooste>
    <asi:Allekirjoittaja>
      <org:Henkilo>
        <org1:AsemaTeksti>Bostads-, energi- och miljöminister</org1:AsemaTeksti>
        <org1:SukuNimi>Kimmo Tiilikainen</org1:SukuNimi>
      </org:Henkilo>
    </asi:Allekirjoittaja>
    <asi:Allekirjoittaja>
      <org:Henkilo>
        <org1:AsemaTeksti>Regeringssekreterare</org1:AsemaTeksti>
        <org1:SukuNimi>Ella Särkkä</org1:SukuNimi>
      </org:Henkilo>
    </asi:Allekirjoittaja>
  </asi:AllekirjoitusOsa>
  <asi:LiiteOsa>
    <asi:SisaltoLiite>
      <sis:KappaleKooste>
        <sis1:KursiiviTeksti>Bilaga 4</sis1:KursiiviTeksti>
      </sis:KappaleKooste>
      <sis:KappaleKooste>Särskilda krav som gäller godkännande av kvicksilveravfall för tillfällig lagring och bortskaffande</sis:KappaleKooste>
      <sis:KappaleKooste>Vid godkännande av kvicksilveravfall för tillfällig lagring och bortskaffande i mer än ett år ska följande särskilda krav iakttas:</sis:KappaleKooste>
      <sis:KappaleKooste>1<sis1:LihavaTeksti>.</sis1:LihavaTeksti> Kvicksilveravfallets sammansättning</sis:KappaleKooste>
      <sis:KappaleKooste>Kvicksilveravfall ska uppfylla följande krav:</sis:KappaleKooste>
      <sis:KappaleKooste>– en kvicksilverhalt på mer än 99,9 viktprocent,</sis:KappaleKooste>
      <sis:KappaleKooste>– det får inte innehålla föroreningar som kan korrodera kolstål eller rostfritt stål (t.ex. salpetersyra och kloridsaltlösningar).</sis:KappaleKooste>
      <sis:KappaleKooste>2<sis1:LihavaTeksti>.</sis1:LihavaTeksti> Inneslutning</sis:KappaleKooste>
      <sis:KappaleKooste>Behållare som används för tillfällig lagring och bortskaffande av kvicksilveravfall ska vara korrosions- och stötsäkra. Svetsfogar ska därför undvikas. Behållarna ska i synnerhet uppfylla följande krav:</sis:KappaleKooste>
      <sis:KappaleKooste>– behållarmaterial: kolstål (minst ASTM A36) eller rostfritt stål (AISI 304, 316L),</sis:KappaleKooste>
      <sis:KappaleKooste>– behållarna ska vara gas- och vätsketäta,</sis:KappaleKooste>
      <sis:KappaleKooste>– behållarens utsida ska vara beständig mot lagringsförhållandena,</sis:KappaleKooste>
      <sis:KappaleKooste>– behållarens konstruktionstyp ska klara fallprov och täthetsprov enligt kapitel 6.1.5.3 och 6.1.5.4 i Förenta Nationernas rekommendationer om transport av farligt gods, testhandboken.</sis:KappaleKooste>
      <sis:KappaleKooste>Behållarens fyllnadsgrad får vara högst 80 volymprocent för att säkerställa att tillräckligt tomrum finns tillgängligt och att varken läckor eller permanent deformering av behållaren kan inträffa till följd av att vätskan expanderar på grund av hög temperatur.</sis:KappaleKooste>
      <sis:KappaleKooste>3<sis1:LihavaTeksti>.</sis1:LihavaTeksti> Godkännande av tillfällig lagring och bortskaffande</sis:KappaleKooste>
      <sis:KappaleKooste>Behållare som innehåller kvicksilveravfall får godkännas för tillfällig lagring och bortskaffande endast om de uppfyller de krav som anges i denna punkt och om det finns sådana intyg enligt 4 punkten i denna bilaga på att behållarna överensstämmer med kraven som har utfärdats av avfallsproducenten eller den person som är ansvarig för avfallshanteringen av kvicksilveravfall.</sis:KappaleKooste>
      <sis:KappaleKooste>Godkännandeförfarandena ska uppfylla följande krav:</sis:KappaleKooste>
      <sis:KappaleKooste>– endast kvicksilveravfall som uppfyller de krav som avses i punkt 1 i denna bilaga får godkännas,</sis:KappaleKooste>
      <sis:KappaleKooste>– behållarna ska undergå okulär besiktning före lagringen och bortskaffandet och skadade, läckande eller korroderade behållare ska inte godtas,</sis:KappaleKooste>
      <sis:KappaleKooste>– behållarna ska vara försedda med en hållbar stämpel som är tryck i metallens yta och som anger behållarens identifieringsnummer, konstruktionsmaterialet, tomvikten, tillverkarens uppgifter och konstruktionsdatumet,</sis:KappaleKooste>
      <sis:KappaleKooste>– behållarna ska vara försedda med en permanent monterad plakett där referensnumret på det intyg som nämns i 4 punkten i denna bilaga anges.</sis:KappaleKooste>
      <sis:KappaleKooste>4<sis1:LihavaTeksti>.</sis1:LihavaTeksti> Intyg</sis:KappaleKooste>
      <sis:KappaleKooste>Ett intyg ska innehålla följande uppgifter:</sis:KappaleKooste>
      <sis:KappaleKooste>– avfallsproducentens namn och adress,</sis:KappaleKooste>
      <sis:KappaleKooste>– namn och adress på den person som är ansvarig för deponeringen av behållarna,</sis:KappaleKooste>
      <sis:KappaleKooste>– plats och datum för deponeringen,</sis:KappaleKooste>
      <sis:KappaleKooste>– mängden kvicksilveravfall,</sis:KappaleKooste>
      <sis:KappaleKooste>– kvicksilveravfallets renhetsgrad och, om relevant, en redogörelse för föroreningarna, inklusive analysrapporten,</sis:KappaleKooste>
      <sis:KappaleKooste>– bekräftelse av att behållarna har använts uteslutande för transport och tillfällig lagring av kvicksilveravfall,</sis:KappaleKooste>
      <sis:KappaleKooste>– behållarnas identifieringsnummer,</sis:KappaleKooste>
      <sis:KappaleKooste>– eventuella särskilda kommentarer.</sis:KappaleKooste>
    </asi:SisaltoLiite>
  </asi:LiiteOsa>
</vah:VahvistettavaLaki>
